fc_xd_bigdate3.py
fc_bigdate3-1.0.dist-info/METADATA
fc_bigdate3-1.0.dist-info/WHEEL
fc_bigdate3-1.0.dist-info/top_level.txt
fc_bigdate3-1.0.dist-info/RECORD
